.VERSION
AUTHORS.rst
CONTRIBUTING.rst
HISTORY.rst
LICENSE
MANIFEST.in
README.rst
USAGE.rst
requirements.txt
setup.cfg
setup.py
certbotlib/.VERSION
certbotlib/__init__.py
certbotlib/_version.py
certbotlib/certbotlib.py
certbotlib/certbotlibexceptions.py
certbotlib/test_cert.py
certbotlib.egg-info/PKG-INFO
certbotlib.egg-info/SOURCES.txt
certbotlib.egg-info/dependency_links.txt
certbotlib.egg-info/not-zip-safe
certbotlib.egg-info/requires.txt
certbotlib.egg-info/top_level.txt
docs/Makefile
docs/authors.rst
docs/conf.py
docs/contributing.rst
docs/history.rst
docs/index.rst
docs/installation.rst
docs/readme.rst
docs/usage.rst
requirements/development.txt
requirements/documentation.txt
requirements/testing.txt