Metadata-Version: 1.1
Name: certbotlib
Version: 0.1.0
Summary: A wrapper for Certbot CLI
Home-page: https://github.com/whoever/whatever
Author: Oriol Fabregas
Author-email: oriol.fabregas@payconiq.com
License: MIT
Keywords: certbotlib
Platform: UNKNOWN
Classifier: Development Status :: 4 - Beta
Classifier: Intended Audience :: Developers
Classifier: License :: OSI Approved :: MIT License
Classifier: Natural Language :: English
Classifier: Programming Language :: Python
